vim_prompt/__init__.py
vim_prompt/fzf.py
vim_prompt/rofi.py
vim_prompt/assets/icon.png
vim_prompt/db/commands.json
vim_prompt-0.1.3.dist-info/LICENSE
vim_prompt-0.1.3.dist-info/METADATA
vim_prompt-0.1.3.dist-info/WHEEL
vim_prompt-0.1.3.dist-info/entry_points.txt
vim_prompt-0.1.3.dist-info/top_level.txt
vim_prompt-0.1.3.dist-info/RECORD
