Metadata-Version: 2.2
Name: vim-prompt
Version: 0.1.3
Summary: A Vim cheatsheet prompter and command browser using rofi/fzf
Home-page: https://github.com/ubuntupunk/vim-prompt
Author: Ubuntupunk
Author-email: ubuntupunk@gmail.com
Classifier: Programming Language :: Python :: 3
Classifier: License :: OSI Approved :: MIT License
Classifier: Operating System :: POSIX :: Linux
Requires-Python: >=3.6
License-File: LICENSE
Provides-Extra: dev
Requires-Dist: pytest; extra == "dev"
Requires-Dist: pytest-cov; extra == "dev"
Dynamic: author
Dynamic: author-email
Dynamic: classifier
Dynamic: description
Dynamic: description-content-type
Dynamic: home-page
Dynamic: provides-extra
Dynamic: requires-python
Dynamic: summary
